<?xml version="1.0" encoding="UTF-8"?>
<CristinaParams>
<param>
<index>0</index>
<name>x0</name>
<value>0</value>
<type>int</type>
<gap>1</gap>
<min_value>-100</min_value>
<max_value>100</max_value>
</param>
<param>
<index>1</index>
<name>x1</name>
<value>0</value>
<type>int</type>
<gap>1</gap>
<min_value>-100</min_value>
<max_value>100</max_value>
</param>
<param>
<index>2</index>
<name>x2</name>
<value>0</value>
<type>int</type>
<gap>1</gap>
<min_value>-100</min_value>
<max_value>100</max_value>
</param>
<param>
<index>3</index>
<name>x3</name>
<value>0</value>
<type>int</type>
<gap>1</gap>
<min_value>-100</min_value>
<max_value>100</max_value>
</param>
<param>
<index>4</index>
<name>x4</name>
<value>0</value>
<type>int</type>
<gap>1</gap>
<min_value>-100</min_value>
<max_value>100</max_value>
</param>
</CristinaParams>
